{"codeReference": "235", "nameReference": "Melancia", "group": "FRUTAS", "itemHint": [{"name": "Laranja", "code": "208", "score": 0.18408399568246692, "semaphore": "green"}, {"name": "Mamão", "code": "225", "score": 0.5000044602635143, "semaphore": "yellow"}, {"name": "Tangerina", "code": "251", "score": 0.5590137465321474, "semaphore": "yellow"}, {"name": "Abacaxi", "code": "164", "score": 0.6502038340425182, "semaphore": "yellow"}, {"name": "Banana prata", "code": "182", "score": 1.0, "semaphore": "red"}]}