{"codeReference": "650080299", "nameReference": "Farinha de milho floco para cuscuz", "group": "FARINHAS", "itemHint": [{"name": "Farinha de trigo branca com fermento", "code": "35", "score": 0.14717054526657658, "semaphore": "green"}, {"name": "Fubá de milho", "code": "43", "score": 0.27861392049261857, "semaphore": "green"}, {"name": "Aveia em flocos finos", "code": "7", "score": 0.4571744090726335, "semaphore": "yellow"}, {"name": "Farinha de mandioca", "code": "122", "score": 0.49543903366558634, "semaphore": "yellow"}, {"name": "Maisena", "code": "42", "score": 0.5428255909273665, "semaphore": "yellow"}]}